reddit_export/__init__.py
reddit_export/scrape.py
reddit_export/vocabulary.py
reddit_export-0.2.2.dist-info/entry_points.txt
reddit_export-0.2.2.dist-info/licenses/LICENSE.md
reddit_export-0.2.2.dist-info/WHEEL
reddit_export-0.2.2.dist-info/METADATA
reddit_export-0.2.2.dist-info/RECORD
